litedb/__init__.py
litedb/abc/__init__.py
litedb/abc/database.py
litedb/abc/index_manager.py
litedb/abc/table.py
litedb/database/__init__.py
litedb/database/config.py
litedb/database/disk_database.py
litedb/database/memory_database.py
litedb/errors/__init__.py
litedb/errors/errors.py
litedb/index/__init__.py
litedb/index/index.py
litedb/index/memory_index.py
litedb/index/persistent_index.py
litedb/shard/__init__.py
litedb/shard/buffer.py
litedb/shard/manager.py
litedb/shard/shard.py
litedb/shard/shardlru.py
litedb/table/__init__.py
litedb/table/memory_table.py
litedb/table/persistent_table.py
litedb/utils/__init__.py
litedb/utils/checksum.py
litedb/utils/index.py
litedb/utils/io.py
litedb/utils/path.py
litedb/utils/serialization.py
litedb-1.1.0.dist-info/LICENSE
litedb-1.1.0.dist-info/METADATA
litedb-1.1.0.dist-info/WHEEL
litedb-1.1.0.dist-info/top_level.txt
litedb-1.1.0.dist-info/RECORD
