Metadata-Version: 2.1
Name: litedb
Version: 1.1.0
Summary: A pure Python NoSQL database
Home-page: https://github.com/JonathanVusich/litedb
Author: Jonathan Vusich
Author-email: jonathanvusich@gmail.com
License: MIT
Keywords: nosql database python
Platform: UNKNOWN
Classifier: Development Status :: 4 - Beta
Classifier: Topic :: Database
Classifier: License :: OSI Approved :: MIT License
Requires-Dist: sortedcontainers
